Swit/Switter.py
Swit/__init__.py
Swit/common/__init__.py
Swit/common/exceptions.py
Swit/common/helper_funcs.py
Swit/common/paths.py
Swit/inner/__init__.py
Swit/inner/add.py
Swit/inner/branch.py
Swit/inner/checkout.py
Swit/inner/commit.py
Swit/inner/graph.py
Swit/inner/init.py
Swit/inner/merge.py
Swit/inner/status.py
Swit-0.32.dist-info/LICENSE
Swit-0.32.dist-info/METADATA
Swit-0.32.dist-info/WHEEL
Swit-0.32.dist-info/entry_points.txt
Swit-0.32.dist-info/top_level.txt
Swit-0.32.dist-info/RECORD
